PyPerspective/Perspective.py
PyPerspective/__init__.py
PyPerspective/errors.py
PyPerspective-1.0.4.dist-info/LICENSE.txt
PyPerspective-1.0.4.dist-info/METADATA
PyPerspective-1.0.4.dist-info/WHEEL
PyPerspective-1.0.4.dist-info/top_level.txt
PyPerspective-1.0.4.dist-info/RECORD
