Metadata-Version: 2.1
Name: PyPerspective
Version: 1.0.4
Summary: A Basic Library For Perspective API Usage
Home-page: https://github.com/TunayAdaKaracan/PyPerspective
Author: Tunay Ada Karacan
Author-email: tunayada@gmail.com
License: MIT
Platform: UNKNOWN
Classifier: Development Status :: 4 - Beta
Classifier: Intended Audience :: Education
Classifier: License :: OSI Approved :: MIT License
Classifier: Natural Language :: Turkish
Classifier: Operating System :: Microsoft :: Windows
Classifier: Operating System :: POSIX :: Linux
Classifier: Operating System :: MacOS
Classifier: Programming Language :: Python :: 3.8
Requires-Dist: requests
